tpds_extension/cryptoquantique_quarklink/extension.yaml
tpds_extension/cryptoquantique_quarklink/setup.py
tpds_extension/cryptoquantique_quarklink/version.py
tpds_extension/cryptoquantique_quarklink/TrustFlex/Quarklink Connect-Custom PKI-TFLEX.ipynb
tpds_extension/cryptoquantique_quarklink/TrustFlex/cust_def_device.c
tpds_extension/cryptoquantique_quarklink/TrustFlex/cust_def_device.h
tpds_extension/cryptoquantique_quarklink/TrustFlex/cust_def_signer.c
tpds_extension/cryptoquantique_quarklink/TrustFlex/cust_def_signer.h
tpds_extension/cryptoquantique_quarklink/TrustFlex/firmware.zip
tpds_extension/cryptoquantique_quarklink/TrustFlex/project_config.h
tpds_extension/cryptoquantique_quarklink/TrustFlex/ql_connect.h
tpds_extension/cryptoquantique_quarklink/TrustFlex/assets/Custom PKI Quarklink.md
tpds_extension/cryptoquantique_quarklink/TrustFlex/assets/quarklink_iotconnect_trust.ui
tpds_extension/cryptoquantique_quarklink/TrustFlex/assets/shield.ico
tpds_extension/cryptoquantique_quarklink/TrustFlex/assets/Quarklink_CLI/quarklink.exe
tpds_extension/cryptoquantique_quarklink/TrustFlex/assets/images/assets_custompki_quarklink.png
tpds_extension/cryptoquantique_quarklink/TrustFlex/assets/images/aws_ttlog.png
tpds_extension/cryptoquantique_quarklink/TrustFlex/assets/images/board_stack.png
tpds_extension/cryptoquantique_quarklink/TrustFlex/assets/images/c-snippet.png
tpds_extension/cryptoquantique_quarklink/TrustFlex/assets/images/crypto_quantique.png
tpds_extension/cryptoquantique_quarklink/TrustFlex/assets/images/help_check.png
tpds_extension/cryptoquantique_quarklink/TrustFlex/assets/images/help_copy.png
tpds_extension/cryptoquantique_quarklink/TrustFlex/assets/images/help_cpid.png
tpds_extension/cryptoquantique_quarklink/TrustFlex/assets/images/help_createca1.png
tpds_extension/cryptoquantique_quarklink/TrustFlex/assets/images/help_createca2.png
tpds_extension/cryptoquantique_quarklink/TrustFlex/assets/images/help_createdev.png
tpds_extension_cryptoquantique_quarklink-1.0.3.dist-info/METADATA
tpds_extension_cryptoquantique_quarklink-1.0.3.dist-info/WHEEL
tpds_extension_cryptoquantique_quarklink-1.0.3.dist-info/top_level.txt
tpds_extension_cryptoquantique_quarklink-1.0.3.dist-info/RECORD
